[
  {
    "title": "TECH SKILLS:",
    "skillsList": [
      "HTML / CSS / SASS",
      "GIT",
      "JavaScript",
      "TypeScript",
      "React / React native",
      "Redux",
      "Next",
      "Node",
      "Nest"
    ]
  },
  {
    "title": "SOFT SKILLS:",
    "skillsList": [
      "Analytical thinking",
      "Positive attitude",
      "Communicative",
      "Conscientious",
      "Eager to learn"
    ]
  },
  {
    "title": "LANGUAGE SKILLS:",
    "skillsList": ["English - Pre-intermediate", "Ukrainian - Native"]
  },
  {
    "title": "LAST CV UPDATE DATE:",
    "skillsList": [
      "16.12.2025",
      "12.11.2024",
      "15.10.2024",
      "24.07.2024",
      "03.08.2023",
      "02.03.2023"
    ]
  }
]
